async_services/__init__.py
async_services/core/__init__.py
async_services/core/exceptions.py
async_services/core/manager.py
tests/__init__.py
tests/test_core.py
async_services-1.0.1.dist-info/LICENSE.md
async_services-1.0.1.dist-info/METADATA
async_services-1.0.1.dist-info/WHEEL
async_services-1.0.1.dist-info/top_level.txt
async_services-1.0.1.dist-info/RECORD
