Metadata-Version: 2.1
Name: async-services
Version: 1.0.1
Summary: Synchronus Wrapper for Async Code
Home-page: https://github.com/gekco/async_services
Author: Ankit Kathuria
Author-email: ankitkathuria534@gmail.com
License: MIT
Platform: UNKNOWN
Classifier: License :: OSI Approved :: MIT License
Classifier: Programming Language :: Python :: 3
Classifier: Programming Language :: Python :: 3.7
